{
  "content-name": "forfeits",
  "card-count": "15",
  "card-color": "#535353",
  "motifs": [
    "categories.png",
    "groupcocktail.png",
    "doubletrouble.png",
    "doashot.png",
    "countdown.png",
    "waterfall.png",
    "finishdrink.png",
    "drinkingbuddy.png",
    "takeasip.png",
    "sipandspin.png",
    "onehandwonder.png",
    "aroundtheworld.png",
    "pickyourpoison.png",
    "accentround.png",
    "chugrelay.png"
  ],
  "titles": [
    "Categories",
    "Group Cocktail",
    "Double Trouble",
    "Do A Shot",
    "Countdown",
    "Waterfall",
    "Finish Drink",
    "Drinking Buddy",
    "Take A Sip",
    "Sip & Spin",
    "One Hand Wonder",
    "Around the World",
    "Pick Your Poison",
    "Accent Round",
    "Chug Relay"
  ],
  "cards": [
    "The group decides a category, you have 30s to name as many thing as possible",
    "All the players must mix their drinks into one, thats your drink!",
    "Two shots back to back!",
    "Do a Shot!",
    "You must sip your drink for 10s",
    "Everyone starts drinking; you can only stop when the person to your left does!",
    "You must finish your drink",
    "For the next round you must drink when anyone else does",
    "Have a sip of your drink",
    "Take a shot then spin round 15 times",
    "Use your non dominant hand to hold your drink for the next round",
    "Take a sip from every players drink",
    "The group chooses your next drink",
    "Speak in a different accent for the next round, if you mess up - drink!",
    "You and another player both chug your drinks. Whever finished last does the winners next forfeit",
  ],
  "timers": [
    "30",
    "0",
    "0",
    "0",
    "10",
    "0",
    "0",
    "0",
    "0",
    "0",
    "0",
    "0",
    "0",
    "0",
    "0"
  ]
}